{
  "$schema" : "http://json-schema.org/draft-07/schema#",
  "$id" : "urn:a5x:ex5:schema:v1:business:LegalPerson",
  "$metadata" : {
    "domain" : "business",
    "schemaId" : "urn:a5x:ex5:schema:v1:business:LegalPerson"
  },
  "title" : "Legal Person",
  "description" : "Legal Person",
  "type" : "object",
  "properties" : {
    "legalPersonInformation" : {
      "$ref" : "../../objects/business/LegalPersonRelationship.json"
    },
    "legalEntitySpecific" : {
      "$ref" : "../../objects/business/LegalEntitySpecific.json"
    },
    "accountDetails" : {
      "$ref" : "../../objects/business/AccountDetails.json",
      "description" : "Legal person information"
    },
    "relationship" : {
      "type" : "array",
      "items" : {
        "$ref" : "../../objects/business/RelationshipData.json",
        "description" : "Type of relationship",
        "$comment" : "Consult External Code List table ExternalQualificationCode"
      },
      "description" : "Array of relationship data - allows multiple relationships"
    }
  },
  "required" : [ "legalPersonInformation", "legalEntitySpecific", "accountDetails" ],
  "additionalProperties" : false,
  "examples" : [ {
    "legalPersonInformation" : {
      "corporateName" : "Empresa XPTO Ltda",
      "personBase" : {
        "principalDocument" : {
          "documentType" : 2,
          "documentNumber" : "12345678900"
        },
        "politicallyExposedPerson" : false,
        "usPerson" : false,
        "relatedPerson" : true,
        "countryOfResidence" : "BRA",
        "registrationUpdateDate" : "2024-01-15",
        "address" : {
          "street" : "Rua Brasil창ndia",
          "number" : "123",
          "complement" : "Apto 101",
          "neighborhood" : "Centro",
          "postalCode" : "01234-567",
          "cityName" : 3550308,
          "state" : "SP",
          "country" : "BRA",
          "phoneNumber" : "+55-11-91234-5678",
          "email" : "usuario@exemplo.com.br"
        }
      },
      "isNonProfit" : false
    },
    "legalEntitySpecific" : {
      "statusNIF" : "SIM",
      "economicActivity" : "6201-5/01",
      "nonResidentClassification" : 1,
      "revenue" : {
        "amount" : "1000000.00",
        "currency" : "BRL"
      },
      "patrimony" : {
        "amount" : "5000000.00",
        "currency" : "BRL"
      },
      "exclusiveFund" : true,
      "exclusiveFundData" : {
        "personType" : 1,
        "residenceStatus" : "RESI",
        "documentIdentifier" : {
          "documentType" : 2,
          "documentNumber" : "12345678901"
        },
        "relatedPerson" : false,
        "politicallyExposedPerson" : false,
        "usPerson" : false,
        "countryOfResidence" : "BRA"
      },
      "nonResidentBeneficialOwner" : false,
      "isNonProfit" : false
    },
    "accountDetails" : {
      "personStatus" : 1,
      "reasonCode" : 1,
      "simplifiedRegistrationForNonResident" : false,
      "foreignIntermediaryName" : "XPTO Bank",
      "accountData" : {
        "profile" : 1,
        "riskProfile" : 1,
        "status" : 1,
        "onBehalfOf" : true,
        "openedOnBehalf" : false,
        "intermediaryCode" : false
      },
      "internationalCollateral" : {
        "jurisdictionOfOrigin" : "USA",
        "legalForm" : "LLC",
        "beneficiaryBankDetails" : {
          "accountNumber" : "DE89370400440532013000",
          "iban" : "DE89370400440532013000",
          "swiftCode" : "DXXXXXXF",
          "name" : {
            "bankName" : "Example Bank"
          },
          "bankCountry" : "BRA"
        },
        "transferCurrency" : 220,
        "intermediaryBankDetails" : {
          "accountNumber" : "DE89370400440532013000",
          "iban" : "DE89370400440532013000",
          "swiftCode" : "DXXXXXXF",
          "name" : {
            "bankName" : "Example Bank"
          },
          "bankCountry" : "BRA"
        }
      },
      "documents" : [ {
        "documentIdentifier" : {
          "documentType" : 2,
          "documentNumber" : "12345678900"
        },
        "issueDate" : "2018-05-15",
        "expirationDate" : "2028-05-14",
        "country" : "BRA",
        "IssuingAuthority" : 2
      } ]
    },
    "relationship" : [ {
      "relationshipType" : 1,
      "naturalPersonRelationship" : {
        "name" : {
          "fullName" : "Jo찾o Oliveira Santos",
          "socialName" : "Maria Oliveira Santos",
          "motherOrGuardian" : "Ana Maria de Souza"
        },
        "personBase" : {
          "principalDocument" : {
            "documentType" : 2,
            "documentNumber" : "12345678900"
          },
          "politicallyExposedPerson" : false,
          "usPerson" : false,
          "relatedPerson" : true,
          "countryOfResidence" : "BRA",
          "registrationUpdateDate" : "2024-01-15",
          "address" : {
            "street" : "Rua Brasil창ndia",
            "number" : "123",
            "complement" : "Apto 101",
            "neighborhood" : "Centro",
            "postalCode" : "01234-567",
            "cityName" : 3550308,
            "state" : "SP",
            "country" : "BRA",
            "phoneNumber" : "+55-11-91234-5678",
            "email" : "usuario@exemplo.com.br"
          }
        }
      }
    }, {
      "relationshipType" : 2,
      "legalPersonRelationship" : {
        "corporateName" : "Empresa XPTO Ltda",
        "personBase" : {
          "principalDocument" : {
            "documentType" : 2,
            "documentNumber" : "12345678900"
          },
          "politicallyExposedPerson" : false,
          "usPerson" : false,
          "relatedPerson" : true,
          "countryOfResidence" : "BRA",
          "registrationUpdateDate" : "2024-01-15",
          "address" : {
            "street" : "Rua Brasil창ndia",
            "number" : "123",
            "complement" : "Apto 101",
            "neighborhood" : "Centro",
            "postalCode" : "01234-567",
            "cityName" : 3550308,
            "state" : "SP",
            "country" : "BRA",
            "phoneNumber" : "+55-11-91234-5678",
            "email" : "usuario@exemplo.com.br"
          }
        },
        "isNonProfit" : false
      }
    } ]
  } ]
}