{
  "$schema" : "http://json-schema.org/draft-07/schema#",
  "$id" : "urn:a5x:ex5:schema:v1:business:ParticipantAndAccount",
  "$metadata" : {
    "domain" : "business",
    "schemaId" : "urn:a5x:ex5:schema:v1:business:ParticipantAndAccount"
  },
  "title" : "Participant and Account Identification",
  "description" : "Participant identification containing participant and account information",
  "type" : "object",
  "properties" : {
    "participantIdentification" : {
      "$ref" : "../../objects/business/PartyId.json",
      "description" : "Provides details about the participant identification"
    },
    "accountIdentification" : {
      "$ref" : "../../objects/business/AccountIdentification.json",
      "description" : "Provides details about the account identification"
    }
  },
  "required" : [ "participantIdentification", "accountIdentification" ],
  "additionalProperties" : false,
  "examples" : [ {
    "participantIdentification" : {
      "id" : 789012,
      "category" : 3
    },
    "accountIdentification" : {
      "id" : 123456789
    }
  } ]
}